cgo_mkto_api_aastudillocgo/__init__.py
cgo_mkto_api_aastudillocgo/mkto_api.py
cgo_mkto_api_aastudillocgo-0.1.28.dist-info/LICENSE
cgo_mkto_api_aastudillocgo-0.1.28.dist-info/METADATA
cgo_mkto_api_aastudillocgo-0.1.28.dist-info/WHEEL
cgo_mkto_api_aastudillocgo-0.1.28.dist-info/top_level.txt
cgo_mkto_api_aastudillocgo-0.1.28.dist-info/RECORD
