Metadata-Version: 2.1
Name: cgo_mkto_api_aastudillocgo
Version: 0.1.28
Summary: A package to use the bulk API of Marketo, designed for Citizengo
Author-email: Angel Xavier Astudillo Aguilar <aastudillo@citizengo.net>
Project-URL: Homepage, https://citizengo.org/en-us
Classifier: Programming Language :: Python :: 3
Classifier: License :: OSI Approved :: MIT License
Classifier: Operating System :: OS Independent
Requires-Python: >=3.7
License-File: LICENSE
